.DS_Store
memory_game/__init__.py
memory_game/game.py
memory_game-0.3.dist-info/LICENSE
memory_game-0.3.dist-info/METADATA
memory_game-0.3.dist-info/WHEEL
memory_game-0.3.dist-info/entry_points.txt
memory_game-0.3.dist-info/top_level.txt
memory_game-0.3.dist-info/RECORD
