Metadata-Version: 2.1
Name: memory_game
Version: 0.3
Summary: A simple console-based memory game
Home-page: https://github.com/oridemitsuhiko
Author: Your Name
Author-email: your.email@example.com
License: MIT
Classifier: Programming Language :: Python :: 3
Classifier: License :: OSI Approved :: MIT License
Classifier: Operating System :: OS Independent
Requires-Python: >=3.6
License-File: LICENSE
